wattpad_ebook/__init__.py
wattpad_ebook/wattpad_ebook.py
wattpad_ebook-1.0.2.dist-info/LICENSE
wattpad_ebook-1.0.2.dist-info/METADATA
wattpad_ebook-1.0.2.dist-info/WHEEL
wattpad_ebook-1.0.2.dist-info/entry_points.txt
wattpad_ebook-1.0.2.dist-info/top_level.txt
wattpad_ebook-1.0.2.dist-info/RECORD
